Changelog.rst
Developer_Manual.rst
LICENSE.txt
MANIFEST.in
README.rst
pyproject.toml
setup.cfg
setup.py
Gon/Builtins.py
Gon/BytecodeCaching.py
Gon/Bytecodes.py
Gon/CacheCleanup.py
Gon/Constants.py
Gon/EncryptedHUNTER.py
Gon/Errors.py
Gon/HardImportRegistry.py
Gon/MainControl.py
Gon/ModuleRegistry.py
Gon/OptionParsing.py
Gon/Options.py
Gon/OutputDirectories.py
Gon/PostProcessing.py
Gon/Progress.py
Gon/PythonFlavors.py
Gon/PythonOperators.py
Gon/PythonVersions.py
Gon/Serialization.py
Gon/SourceCodeReferences.py
Gon/Tracing.py
Gon/TreeXML.py
Gon/Variables.py
Gon/Version.py
Gon/__init__.py
Gon/__main__.py
Gon/__past__.py
Gon/build/Backend.scons
Gon/build/CCompilerVersion.scons
Gon/build/DataComposerInterface.py
Gon/build/Offsets.scons
Gon/build/Onefile.scons
Gon/build/SconsCaching.py
Gon/build/SconsCompilerSettings.py
Gon/build/SconsHacks.py
Gon/build/SconsInterface.py
Gon/build/SconsProgress.py
Gon/build/SconsSpawn.py
Gon/build/SconsUtils.py
Gon/build/__init__.py
Gon/build/include/Gon/allocator.h
Gon/build/include/Gon/builtins.h
Gon/build/include/Gon/calling.h
Gon/build/include/Gon/checkers.h
Gon/build/include/Gon/checksum_tools.h
Gon/build/include/Gon/compiled_asyncgen.h
Gon/build/include/Gon/compiled_cell.h
Gon/build/include/Gon/compiled_coroutine.h
Gon/build/include/Gon/compiled_frame.h
Gon/build/include/Gon/compiled_function.h
Gon/build/include/Gon/compiled_generator.h
Gon/build/include/Gon/compiled_method.h
Gon/build/include/Gon/constants.h
Gon/build/include/Gon/constants_blob.h
Gon/build/include/Gon/debug_settings.h
Gon/build/include/Gon/environment_variables.h
Gon/build/include/Gon/environment_variables_system.h
Gon/build/include/Gon/exception_groups.h
Gon/build/include/Gon/exceptions.h
Gon/build/include/Gon/filesystem_paths.h
Gon/build/include/Gon/freelists.h
Gon/build/include/Gon/hedley.h
Gon/build/include/Gon/helpers.h
Gon/build/include/Gon/importing.h
Gon/build/include/Gon/incbin.h
Gon/build/include/Gon/jit_sources.h
Gon/build/include/Gon/prelude.h
HxHGoN.egg-info/PKG-INFO
HxHGoN.egg-info/PKG-INFO.bak
HxHGoN.egg-info/SOURCES.txt
HxHGoN.egg-info/dependency_links.txt
HxHGoN.egg-info/entry_points.txt
HxHGoN.egg-info/not-zip-safe
HxHGoN.egg-info/requires.txt
HxHGoN.egg-info/top_level.txt
